{
    "id": "53b2317a-44a7-474b-8ec5-e115f31360f8",
    "filename": "Mantel6.jpg",
    "category": "trench coat",
    "sub_category": "parka",
    "gender": "male fashion",
    "primary_color": "khaki",
    "secondary_color": "beige",
    "accent_color": "metallic",
    "pattern": "camouflage",
    "material": "linen",
    "fit": "regular fit",
    "silhouette": "fitted",
    "neckline": "halter",
    "sleeve": "raglan",
    "length": "midi length",
    "rise": "low-rise",
    "closure_type": "buttons",
    "style": "vintage",
    "occasion": "office wear",
    "season": "spring",
    "body_shape": "rectangle",
    "aesthetic_keywords": "monochrome",
    "detail_features": "embellished",
    "upcycling_potential": "medium",
    "upcycling_type": "cut-and-sew",
    "repairability": "moderate repair",
    "sustainability": "recycled fabric",
    "visible_accessories": "handbag"
}